<?xml version="1.0" encoding="UTF-8"?>
<!-- edited with XMLSpy v2013 (http://www.altova.com) by  () -->
<SpriteBox>
	<CharacterSprite>
		<TotalSpriteNumber>1</TotalSpriteNumber>
		<Sprite>
			<SpriteName>test</SpriteName>
			<PictureName>\resource\picture\character\test.png</PictureName>
			<TotalActionNumber>8</TotalActionNumber>
			<width>32</width>
			<height>48</height>
			<Action>
				<ActionName>readyDown</ActionName>
				<FrameDelay>6</FrameDelay>
				<FrameTotal>1</FrameTotal>
				<IsRepeat>true</IsRepeat>
				<RepeatStart>0</RepeatStart>
				<RepeatOver>0</RepeatOver>
				<FrameBox>
					<Frame>
						<x>0</x>
						<y>144</y>
						<rectBox>
							<rectNumber>1</rectNumber>
							<rect>
								<x>0</x>
								<y>0</y>
								<w>20</w>
								<h>30</h>
							</rect>
						</rectBox>
					</Frame>
				</FrameBox>
			</Action>
			<Action>
				<ActionName>readyLeft</ActionName>
				<FrameDelay>6</FrameDelay>
				<FrameTotal>1</FrameTotal>
				<IsRepeat>true</IsRepeat>
				<RepeatStart>0</RepeatStart>
				<RepeatOver>0</RepeatOver>
				<FrameBox>
					<Frame>
						<x>0</x>
						<y>96</y>
						<rectBox>
							<rectNumber>1</rectNumber>
							<rect>
								<x>0</x>
								<y>0</y>
								<w>20</w>
								<h>30</h>
							</rect>
						</rectBox>
					</Frame>
				</FrameBox>
			</Action>
			<Action>
				<ActionName>readyRight</ActionName>
				<FrameDelay>6</FrameDelay>
				<FrameTotal>1</FrameTotal>
				<IsRepeat>true</IsRepeat>
				<RepeatStart>0</RepeatStart>
				<RepeatOver>0</RepeatOver>
				<FrameBox>
					<Frame>
						<x>0</x>
						<y>48</y>
						<rectBox>
							<rectNumber>1</rectNumber>
							<rect>
								<x>0</x>
								<y>0</y>
								<w>20</w>
								<h>30</h>
							</rect>
						</rectBox>
					</Frame>
				</FrameBox>
			</Action>
			<Action>
				<ActionName>readyUp</ActionName>
				<FrameDelay>6</FrameDelay>
				<FrameTotal>1</FrameTotal>
				<IsRepeat>true</IsRepeat>
				<RepeatStart>0</RepeatStart>
				<RepeatOver>0</RepeatOver>
				<FrameBox>
					<Frame>
						<x>0</x>
						<y>0</y>
						<rectBox>
							<rectNumber>1</rectNumber>
							<rect>
								<x>0</x>
								<y>0</y>
								<w>20</w>
								<h>30</h>
							</rect>
						</rectBox>
					</Frame>
				</FrameBox>
			</Action>
			<Action>
				<ActionName>moveDown</ActionName>
				<FrameDelay>6</FrameDelay>
				<FrameTotal>4</FrameTotal>
				<IsRepeat>true</IsRepeat>
				<RepeatStart>0</RepeatStart>
				<RepeatOver>3</RepeatOver>
				<FrameBox>
					<Frame>
						<x>0</x>
						<y>144</y>
						<rectBox>
							<rectNumber>1</rectNumber>
							<rect>
								<x>0</x>
								<y>0</y>
								<w>20</w>
								<h>30</h>
							</rect>
						</rectBox>
					</Frame>
					<Frame>
						<x>32</x>
						<y>144</y>
						<rectBox>
							<rectNumber>1</rectNumber>
							<rect>
								<x>0</x>
								<y>0</y>
								<w>20</w>
								<h>30</h>
							</rect>
						</rectBox>
					</Frame>
					<Frame>
						<x>64</x>
						<y>144</y>
						<rectBox>
							<rectNumber>1</rectNumber>
							<rect>
								<x>0</x>
								<y>0</y>
								<w>20</w>
								<h>30</h>
							</rect>
						</rectBox>
					</Frame>
					<Frame>
						<x>96</x>
						<y>144</y>
						<rectBox>
							<rectNumber>1</rectNumber>
							<rect>
								<x>0</x>
								<y>0</y>
								<w>20</w>
								<h>30</h>
							</rect>
						</rectBox>
					</Frame>
				</FrameBox>
			</Action>
			<Action>
				<ActionName>moveLeft</ActionName>
				<FrameDelay>6</FrameDelay>
				<FrameTotal>4</FrameTotal>
				<IsRepeat>true</IsRepeat>
				<RepeatStart>0</RepeatStart>
				<RepeatOver>3</RepeatOver>
				<FrameBox>
					<Frame>
						<x>0</x>
						<y>96</y>
						<rectBox>
							<rectNumber>1</rectNumber>
							<rect>
								<x>0</x>
								<y>0</y>
								<w>20</w>
								<h>30</h>
							</rect>
						</rectBox>
					</Frame>
					<Frame>
						<x>32</x>
						<y>96</y>
						<rectBox>
							<rectNumber>1</rectNumber>
							<rect>
								<x>0</x>
								<y>0</y>
								<w>20</w>
								<h>30</h>
							</rect>
						</rectBox>
					</Frame>
					<Frame>
						<x>64</x>
						<y>96</y>
						<rectBox>
							<rectNumber>1</rectNumber>
							<rect>
								<x>0</x>
								<y>0</y>
								<w>20</w>
								<h>30</h>
							</rect>
						</rectBox>
					</Frame>
					<Frame>
						<x>96</x>
						<y>96</y>
						<rectBox>
							<rectNumber>1</rectNumber>
							<rect>
								<x>0</x>
								<y>0</y>
								<w>20</w>
								<h>30</h>
							</rect>
						</rectBox>
					</Frame>
				</FrameBox>
			</Action>
			<Action>
				<ActionName>moveRight</ActionName>
				<FrameDelay>6</FrameDelay>
				<FrameTotal>4</FrameTotal>
				<IsRepeat>true</IsRepeat>
				<RepeatStart>0</RepeatStart>
				<RepeatOver>3</RepeatOver>
				<FrameBox>
					<Frame>
						<x>0</x>
						<y>48</y>
						<rectBox>
							<rectNumber>1</rectNumber>
							<rect>
								<x>0</x>
								<y>0</y>
								<w>20</w>
								<h>30</h>
							</rect>
						</rectBox>
					</Frame>
					<Frame>
						<x>32</x>
						<y>48</y>
						<rectBox>
							<rectNumber>1</rectNumber>
							<rect>
								<x>0</x>
								<y>0</y>
								<w>20</w>
								<h>30</h>
							</rect>
						</rectBox>
					</Frame>
					<Frame>
						<x>64</x>
						<y>48</y>
						<rectBox>
							<rectNumber>1</rectNumber>
							<rect>
								<x>0</x>
								<y>0</y>
								<w>20</w>
								<h>30</h>
							</rect>
						</rectBox>
					</Frame>
					<Frame>me>
						<x>96</x>
						<y>48</y>
						<rectBox>
							<rectNumber>1</rectNumber>
							<rect>
								<x>0</x>
								<y>0</y>
								<w>20</w>
								<h>30</h>
							</rect>
						</rectBox>
					</Frame>
				</FrameBox>
			</Action>
			<Action>
				<ActionName>moveUp</ActionName>
				<FrameDelay>6</FrameDelay>
				<FrameTotal>4</FrameTotal>
				<IsRepeat>true</IsRepeat>
				<RepeatStart>0</RepeatStart>
				<RepeatOver>3</RepeatOver>
				<FrameBox>
					<Frame>
						<x>0</x>
						<y>0</y>
						<rectBox>
							<rectNumber>1</rectNumber>
							<rect>
								<x>0</x>
								<y>0</y>
								<w>20</w>
								<h>30</h>
							</rect>
						</rectBox>
					</Frame>
					<Frame>
						<x>32</x>
						<y>0</y>
						<rectBox>
							<rectNumber>1</rectNumber>
							<rect>
								<x>0</x>
								<y>0</y>
								<w>20</w>
								<h>30</h>
							</rect>
						</rectBox>
					</Frame>
					<Frame>
						<x>64</x>
						<y>0</y>
						<rectBox>
							<rectNumber>1</rectNumber>
							<rect>
								<x>0</x>
								<y>0</y>
								<w>20</w>
								<h>30</h>
							</rect>
						</rectBox>
					</Frame>
					<Frame>
						<x>96</x>
						<y>0</y>
						<rectBox>
							<rectNumber>1</rectNumber>
							<rect>
								<x>0</x>
								<y>0</y>
								<w>20</w>
								<h>30</h>
							</rect>
						</rectBox>
					</Frame>
				</FrameBox>
			</Action>
		</Sprite>
	</CharacterSprite>
	<BulletSprite>
		<TotalSpriteNumber>2</TotalSpriteNumber>
		<Sprite>
			<SpriteName>bullet</SpriteName>
			<PictureName>\resource\picture\bullet\bullet.png</PictureName>
			<TotalActionNumber>1</TotalActionNumber>
			<width>57</width>
			<height>61</height>
			<Action>
				<ActionName>bullet</ActionName>
				<FrameDelay>100</FrameDelay>
				<FrameTotal>1</FrameTotal>
				<IsRepeat>false</IsRepeat>
				<RepeatStart>0</RepeatStart>
				<RepeatOver>0</RepeatOver>
				<FrameBox>
					<Frame>
						<x>0</x>
						<y>0</y>
						<rectBox>
							<rectNumber>1</rectNumber>
							<rect>
								<x>0</x>
								<y>0</y>
								<w>47</w>
								<h>51</h>
							</rect>
						</rectBox>
					</Frame>
				</FrameBox>
			</Action>
		</Sprite>
		<Sprite>
			<SpriteName>laser</SpriteName>
			<PictureName>\resource\picture\bullet\laser.png</PictureName>
			<TotalActionNumber>1</TotalActionNumber>
			<width>187</width>
			<height>116</height>
			<Action>
				<ActionName>laser</ActionName>
				<FrameDelay>100</FrameDelay>
				<FrameTotal>1</FrameTotal>
				<IsRepeat>false</IsRepeat>
				<RepeatStart>0</RepeatStart>
				<RepeatOver>0</RepeatOver>
				<FrameBox>
					<Frame>
						<x>0</x>
						<y>0</y>
						<rectBox>
							<rectNumber>1</rectNumber>
							<rect>
								<x>0</x>
								<y>0</y>
								<w>180</w>
								<h>60</h>
							</rect>
						</rectBox>
					</Frame>
				</FrameBox>
			</Action>
		</Sprite>
	</BulletSprite>
	<DecorationSprite>
		<TotalSpriteNumber>59</TotalSpriteNumber>
		<Sprite>
			<SpriteName>door</SpriteName>
			<PictureName>\resource\picture\decoration\door.png</PictureName>
			<TotalActionNumber>2</TotalActionNumber>
			<width>73</width>
			<height>64</height>
			<Action>
				<ActionName>open</ActionName>
				<FrameDelay>20</FrameDelay>
				<FrameTotal>4</FrameTotal>
				<IsRepeat>false</IsRepeat>
				<RepeatStart>0</RepeatStart>
				<RepeatOver>3</RepeatOver>
				<FrameBox>
					<Frame>
						<x>0</x>
						<y>192</y>
						<rectBox>
							<rectNumber>1</rectNumber>
							<rect>
								<x>0</x>
								<y>0</y>
								<w>73</w>
								<h>64</h>
							</rect>
						</rectBox>
					</Frame>
					<Frame>
						<x>0</x>
						<y>128</y>
						<rectBox>
							<rectNumber>1</rectNumber>
							<rect>
								<x>0</x>
								<y>0</y>
								<w>73</w>
								<h>64</h>
							</rect>
						</rectBox>
					</Frame>
					<Frame>
						<x>0</x>
						<y>64</y>
						<rectBox>
							<rectNumber>1</rectNumber>
							<rect>
								<x>0</x>
								<y>0</y>
								<w>73</w>
								<h>64</h>
							</rect>
						</rectBox>
					</Frame>
					<Frame>
						<x>0</x>
						<y>0</y>
						<rectBox>
							<rectNumber>1</rectNumber>
							<rect>
								<x>0</x>
								<y>0</y>
								<w>73</w>
								<h>64</h>
							</rect>
						</rectBox>
					</Frame>
				</FrameBox>
			</Action>
			<Action>
				<ActionName>close</ActionName>
				<FrameDelay>20</FrameDelay>
				<FrameTotal>1</FrameTotal>
				<IsRepeat>false</IsRepeat>
				<RepeatStart>0</RepeatStart>
				<RepeatOver>0</RepeatOver>
				<FrameBox>
					<Frame>
						<x>0</x>
						<y>192</y>
						<rectBox>
							<rectNumber>1</rectNumber>
							<rect>
								<x>0</x>
								<y>0</y>
								<w>73</w>
								<h>64</h>
							</rect>
						</rectBox>
					</Frame>
				</FrameBox>
			</Action>
		</Sprite>
		<Sprite>
			<SpriteName>empty</SpriteName>
			<PictureName>\resource\picture\decoration\empty.png</PictureName>
			<TotalActionNumber>1</TotalActionNumber>
			<width>10</width>
			<height>10</height>
			<Action>
				<ActionName>act1</ActionName>
				<FrameDelay>100</FrameDelay>
				<FrameTotal>1</FrameTotal>
				<IsRepeat>true</IsRepeat>
				<RepeatStart>0</RepeatStart>
				<RepeatOver>0</RepeatOver>
				<FrameBox>
					<Frame>
						<x>0</x>
						<y>0</y>
						<rectBox>
							<rectNumber>1</rectNumber>
							<rect>
								<x>0</x>
								<y>0</y>
								<w>10</w>
								<h>10</h>
							</rect>
						</rectBox>
					</Frame>
				</FrameBox>
			</Action>
		</Sprite>
		<Sprite>
			<SpriteName>scarecrow</SpriteName>
			<PictureName>\resource\picture\decoration\decoration.png</PictureName>
			<TotalActionNumber>1</TotalActionNumber>
			<width>32</width>
			<height>32</height>
			<Action>
				<ActionName>act1</ActionName>
				<FrameDelay>100</FrameDelay>
				<FrameTotal>1</FrameTotal>
				<IsRepeat>true</IsRepeat>
				<RepeatStart>0</RepeatStart>
				<RepeatOver>0</RepeatOver>
				<FrameBox>
					<Frame>
						<x>0</x>
						<y>0</y>
						<rectBox>
							<rectNumber>1</rectNumber>
							<rect>
								<x>0</x>
								<y>-16</y>
								<w>16</w>
								<h>16</h>
							</rect>
						</rectBox>
					</Frame>
				</FrameBox>
			</Action>
		</Sprite>
		<Sprite>
			<SpriteName>holeAutumn</SpriteName>
			<PictureName>\resource\picture\decoration\decoration.png</PictureName>
			<TotalActionNumber>1</TotalActionNumber>
			<width>32</width>
			<height>32</height>
			<Action>
				<ActionName>act1</ActionName>
				<FrameDelay>100</FrameDelay>
				<FrameTotal>1</FrameTotal>
				<IsRepeat>true</IsRepeat>
				<RepeatStart>0</RepeatStart>
				<RepeatOver>0</RepeatOver>
				<FrameBox>
					<Frame>
						<x>32</x>
						<y>0</y>
						<rectBox>
							<rectNumber>1</rectNumber>
							<rect>
								<x>0</x>
								<y>0</y>
								<w>20</w>
								<h>20</h>
							</rect>
						</rectBox>
					</Frame>
				</FrameBox>
			</Action>
		</Sprite>
		<Sprite>
			<SpriteName>woodAutumn</SpriteName>
			<PictureName>\resource\picture\decoration\decoration.png</PictureName>
			<TotalActionNumber>1</TotalActionNumber>
			<width>32</width>
			<height>32</height>
			<Action>
				<ActionName>act1</ActionName>
				<FrameDelay>100</FrameDelay>
				<FrameTotal>1</FrameTotal>
				<IsRepeat>true</IsRepeat>
				<RepeatStart>0</RepeatStart>
				<RepeatOver>0</RepeatOver>
				<FrameBox>
					<Frame>
						<x>64</x>
						<y>0</y>
						<rectBox>
							<rectNumber>1</rectNumber>
							<rect>
								<x>0</x>
								<y>-15</y>
								<w>25</w>
								<h>25</h>
							</rect>
						</rectBox>
					</Frame>
				</FrameBox>
			</Action>
		</Sprite>
		<Sprite>
			<SpriteName>smallStoneAutumn</SpriteName>
			<PictureName>\resource\picture\decoration\decoration.png</PictureName>
			<TotalActionNumber>1</TotalActionNumber>
			<width>32</width>
			<height>32</height>
			<Action>
				<ActionName>act1</ActionName>
				<FrameDelay>100</FrameDelay>
				<FrameTotal>1</FrameTotal>
				<IsRepeat>true</IsRepeat>
				<RepeatStart>0</RepeatStart>
				<RepeatOver>0</RepeatOver>
				<FrameBox>
					<Frame>
						<x>96</x>
						<y>0</y>
						<rectBox>
							<rectNumber>0</rectNumber>
						</rectBox>
					</Frame>
				</FrameBox>
			</Action>
		</Sprite>
		<Sprite>
			<SpriteName>rickAutumn</SpriteName>
			<PictureName>\resource\picture\decoration\decoration.png</PictureName>
			<TotalActionNumber>1</TotalActionNumber>
			<width>32</width>
			<height>32</height>
			<Action>
				<ActionName>act1</ActionName>
				<FrameDelay>100</FrameDelay>
				<FrameTotal>1</FrameTotal>
				<IsRepeat>true</IsRepeat>
				<RepeatStart>0</RepeatStart>
				<RepeatOver>0</RepeatOver>
				<FrameBox>
					<Frame>
						<x>128</x>
						<y>0</y>
						<rectBox>
							<rectNumber>1</rectNumber>
							<rect>
								<x>0</x>
								<y>-13</y>
								<w>25</w>
								<h>25</h>
							</rect>
						</rectBox>
					</Frame>
				</FrameBox>
			</Action>
		</Sprite>
		<Sprite>
			<SpriteName>rickWinter</SpriteName>
			<PictureName>\resource\picture\decoration\decoration.png</PictureName>
			<TotalActionNumber>1</TotalActionNumber>
			<width>32</width>
			<height>32</height>
			<Action>
				<ActionName>act1</ActionName>
				<FrameDelay>100</FrameDelay>
				<FrameTotal>1</FrameTotal>
				<IsRepeat>true</IsRepeat>
				<RepeatStart>0</RepeatStart>
				<RepeatOver>0</RepeatOver>
				<FrameBox>
					<Frame>
						<x>160</x>
						<y>0</y>
						<rectBox>
							<rectNumber>1</rectNumber>
							<rect>
								<x>0</x>
								<y>-13</y>
								<w>25</w>
								<h>25</h>
							</rect>
						</rectBox>
					</Frame>
				</FrameBox>
			</Action>
		</Sprite>
		<Sprite>
			<SpriteName>grain</SpriteName>
			<PictureName>\resource\picture\decoration\decoration.png</PictureName>
			<TotalActionNumber>1</TotalActionNumber>
			<width>32</width>
			<height>32</height>
			<Action>
				<ActionName>act1</ActionName>
				<FrameDelay>100</FrameDelay>
				<FrameTotal>1</FrameTotal>
				<IsRepeat>true</IsRepeat>
				<RepeatStart>0</RepeatStart>
				<RepeatOver>0</RepeatOver>
				<FrameBox>
					<Frame>
						<x>192</x>
						<y>0</y>
						<rectBox>
							<rectNumber>0</rectNumber>
						</rectBox>
					</Frame>
				</FrameBox>
			</Action>
		</Sprite>
		<Sprite>
			<SpriteName>rice</SpriteName>
			<PictureName>\resource\picture\decoration\decoration.png</PictureName>
			<TotalActionNumber>1</TotalActionNumber>
			<width>32</width>
			<height>32</height>
			<Action>
				<ActionName>act1</ActionName>
				<FrameDelay>100</FrameDelay>
				<FrameTotal>1</FrameTotal>
				<IsRepeat>true</IsRepeat>
				<RepeatStart>0</RepeatStart>
				<RepeatOver>0</RepeatOver>
				<FrameBox>
					<Frame>
						<x>224</x>
						<y>0</y>
						<rectBox>
							<rectNumber>0</rectNumber>
						</rectBox>
					</Frame>
				</FrameBox>
			</Action>
		</Sprite>
		<Sprite>
			<SpriteName>iceman</SpriteName>
			<PictureName>\resource\picture\decoration\decoration.png</PictureName>
			<TotalActionNumber>1</TotalActionNumber>
			<width>32</width>
			<height>32</height>
			<Action>
				<ActionName>act1</ActionName>
				<FrameDelay>100</FrameDelay>
				<FrameTotal>1</FrameTotal>
				<IsRepeat>true</IsRepeat>
				<RepeatStart>0</RepeatStart>
				<RepeatOver>0</RepeatOver>
				<FrameBox>
					<Frame>
						<x>0</x>
						<y>32</y>
						<rectBox>
							<rectNumber>1</rectNumber>
							<rect>
								<x>0</x>
								<y>-16</y>
								<w>16</w>
								<h>16</h>
							</rect>
						</rectBox>
					</Frame>
				</FrameBox>
			</Action>
		</Sprite>
		<Sprite>
			<SpriteName>holeWinter</SpriteName>
			<PictureName>\resource\picture\decoration\decoration.png</PictureName>
			<TotalActionNumber>1</TotalActionNumber>
			<width>32</width>
			<height>32</height>
			<Action>
				<ActionName>act1</ActionName>
				<FrameDelay>100</FrameDelay>
				<FrameTotal>1</FrameTotal>
				<IsRepeat>true</IsRepeat>
				<RepeatStart>0</RepeatStart>
				<RepeatOver>0</RepeatOver>
				<FrameBox>
					<Frame>
						<x>32</x>
						<y>32</y>
						<rectBox>
							<rectNumber>1</rectNumber>
							<rect>
								<x>0</x>
								<y>0</y>
								<w>20</w>
								<h>20</h>
							</rect>
						</rectBox>
					</Frame>
				</FrameBox>
			</Action>
		</Sprite>
		<Sprite>
			<SpriteName>woodWinter</SpriteName>
			<PictureName>\resource\picture\decoration\decoration.png</PictureName>
			<TotalActionNumber>1</TotalActionNumber>
			<width>32</width>
			<height>32</height>
			<Action>
				<ActionName>act1</ActionName>
				<FrameDelay>100</FrameDelay>
				<FrameTotal>1</FrameTotal>
				<IsRepeat>true</IsRepeat>
				<RepeatStart>0</RepeatStart>
				<RepeatOver>0</RepeatOver>
				<FrameBox>
					<Frame>
						<x>64</x>
						<y>32</y>
						<rectBox>
							<rectNumber>1</rectNumber>
							<rect>
								<x>0</x>
								<y>-15</y>
								<w>25</w>
								<h>25</h>
							</rect>
						</rectBox>
					</Frame>
				</FrameBox>
			</Action>
		</Sprite>
		<Sprite>
			<SpriteName>smallStoneWinter</SpriteName>
			<PictureName>\resource\picture\decoration\decoration.png</PictureName>
			<TotalActionNumber>1</TotalActionNumber>
			<width>32</width>
			<height>32</height>
			<Action>
				<ActionName>act1</ActionName>
				<FrameDelay>100</FrameDelay>
				<FrameTotal>1</FrameTotal>
				<IsRepeat>true</IsRepeat>
				<RepeatStart>0</RepeatStart>
				<RepeatOver>0</RepeatOver>
				<FrameBox>
					<Frame>
						<x>96</x>
						<y>32</y>
						<rectBox>
							<rectNumber>0</rectNumber>
						</rectBox>
					</Frame>
				</FrameBox>
			</Action>
		</Sprite>
		<Sprite>
			<SpriteName>ice</SpriteName>
			<PictureName>\resource\picture\decoration\decoration.png</PictureName>
			<TotalActionNumber>1</TotalActionNumber>
			<width>32</width>
			<height>32</height>
			<Action>
				<ActionName>act1</ActionName>
				<FrameDelay>100</FrameDelay>
				<FrameTotal>1</FrameTotal>
				<IsRepeat>true</IsRepeat>
				<RepeatStart>0</RepeatStart>
				<RepeatOver>0</RepeatOver>
				<FrameBox>
					<Frame>
						<x>128</x>
						<y>32</y>
						<rectBox>
							<rectNumber>0</rectNumber>
						</rectBox>
					</Frame>
				</FrameBox>
			</Action>
		</Sprite>
		<Sprite>
			<SpriteName>barrelWinter</SpriteName>
			<PictureName>\resource\picture\decoration\decoration.png</PictureName>
			<TotalActionNumber>1</TotalActionNumber>
			<width>32</width>
			<height>32</height>
			<Action>
				<ActionName>act1</ActionName>
				<FrameDelay>100</FrameDelay>
				<FrameTotal>1</FrameTotal>
				<IsRepeat>true</IsRepeat>
				<RepeatStart>0</RepeatStart>
				<RepeatOver>0</RepeatOver>
				<FrameBox>
					<Frame>
						<x>160</x>
						<y>32</y>
						<rectBox>
							<rectNumber>1</rectNumber>
							<rect>
								<x>0</x>
								<y>-13</y>
								<w>25</w>
								<h>25</h>
							</rect>
						</rectBox>
					</Frame>
				</FrameBox>
			</Action>
		</Sprite>
		<Sprite>
			<SpriteName>crossWinter</SpriteName>
			<PictureName>\resource\picture\decoration\decoration.png</PictureName>
			<TotalActionNumber>1</TotalActionNumber>
			<width>32</width>
			<height>32</height>
			<Action>
				<ActionName>act1</ActionName>
				<FrameDelay>100</FrameDelay>
				<FrameTotal>1</FrameTotal>
				<IsRepeat>true</IsRepeat>
				<RepeatStart>0</RepeatStart>
				<RepeatOver>0</RepeatOver>
				<FrameBox>
					<Frame>
						<x>192</x>
						<y>32</y>
						<rectBox>
							<rectNumber>1</rectNumber>
							<rect>
								<x>0</x>
								<y>-16</y>
								<w>16</w>
								<h>16</h>
							</rect>
						</rectBox>
					</Frame>
				</FrameBox>
			</Action>
		</Sprite>
		<Sprite>
			<SpriteName>steleWinter</SpriteName>
			<PictureName>\resource\picture\decoration\decoration.png</PictureName>
			<TotalActionNumber>1</TotalActionNumber>
			<width>32</width>
			<height>32</height>
			<Action>
				<ActionName>act1</ActionName>
				<FrameDelay>100</FrameDelay>
				<FrameTotal>1</FrameTotal>
				<IsRepeat>true</IsRepeat>
				<RepeatStart>0</RepeatStart>
				<RepeatOver>0</RepeatOver>
				<FrameBox>
					<Frame>
						<x>224</x>
						<y>32</y>
						<rectBox>
							<rectNumber>1</rectNumber>
							<rect>
								<x>0</x>
								<y>-16</y>
								<w>16</w>
								<h>16</h>
							</rect>
						</rectBox>
					</Frame>
				</FrameBox>
			</Action>
		</Sprite>
		<Sprite>
			<SpriteName>boardWinter0</SpriteName>
			<PictureName>\resource\picture\decoration\decoration.png</PictureName>
			<TotalActionNumber>1</TotalActionNumber>
			<width>32</width>
			<height>32</height>
			<Action>
				<ActionName>act1</ActionName>
				<FrameDelay>100</FrameDelay>
				<FrameTotal>1</FrameTotal>
				<IsRepeat>true</IsRepeat>
				<RepeatStart>0</RepeatStart>
				<RepeatOver>0</RepeatOver>
				<FrameBox>
					<Frame>
						<x>256</x>
						<y>32</y>
						<rectBox>
							<rectNumber>1</rectNumber>
							<rect>
								<x>0</x>
								<y>-16</y>
								<w>16</w>
								<h>16</h>
							</rect>
						</rectBox>
					</Frame>
				</FrameBox>
			</Action>
		</Sprite>
		<Sprite>
			<SpriteName>boardWinter1</SpriteName>
			<PictureName>\resource\picture\decoration\decoration.png</PictureName>
			<TotalActionNumber>1</TotalActionNumber>
			<width>32</width>
			<height>32</height>
			<Action>
				<ActionName>act1</ActionName>
				<FrameDelay>100</FrameDelay>
				<FrameTotal>1</FrameTotal>
				<IsRepeat>true</IsRepeat>
				<RepeatStart>0</RepeatStart>
				<RepeatOver>0</RepeatOver>
				<FrameBox>
					<Frame>
						<x>288</x>
						<y>32</y>
						<rectBox>
							<rectNumber>1</rectNumber>
							<rect>
								<x>0</x>
								<y>-16</y>
								<w>16</w>
								<h>16</h>
							</rect>
						</rectBox>
					</Frame>
				</FrameBox>
			</Action>
		</Sprite>
		<Sprite>
			<SpriteName>wellWinter</SpriteName>
			<PictureName>\resource\picture\decoration\decoration.png</PictureName>
			<TotalActionNumber>1</TotalActionNumber>
			<width>32</width>
			<height>32</height>
			<Action>
				<ActionName>act1</ActionName>
				<FrameDelay>100</FrameDelay>
				<FrameTotal>1</FrameTotal>
				<IsRepeat>true</IsRepeat>
				<RepeatStart>0</RepeatStart>
				<RepeatOver>0</RepeatOver>
				<FrameBox>
					<Frame>
						<x>320</x>
						<y>32</y>
						<rectBox>
							<rectNumber>1</rectNumber>
							<rect>
								<x>0</x>
								<y>-16</y>
								<w>20</w>
								<h>20</h>
							</rect>
						</rectBox>
					</Frame>
				</FrameBox>
			</Action>
		</Sprite>
		<Sprite>
			<SpriteName>stone0</SpriteName>
			<PictureName>\resource\picture\decoration\decoration.png</PictureName>
			<TotalActionNumber>1</TotalActionNumber>
			<width>32</width>
			<height>32</height>
			<Action>
				<ActionName>act1</ActionName>
				<FrameDelay>100</FrameDelay>
				<FrameTotal>1</FrameTotal>
				<IsRepeat>true</IsRepeat>
				<RepeatStart>0</RepeatStart>
				<RepeatOver>0</RepeatOver>
				<FrameBox>
					<Frame>
						<x>0</x>
						<y>64</y>
						<rectBox>
							<rectNumber>1</rectNumber>
							<rect>
								<x>0</x>
								<y>-10</y>
								<w>25</w>
								<h>25</h>
							</rect>
						</rectBox>
					</Frame>
				</FrameBox>
			</Action>
		</Sprite>
		<Sprite>
			<SpriteName>stone1</SpriteName>
			<PictureName>\resource\picture\decoration\decoration.png</PictureName>
			<TotalActionNumber>1</TotalActionNumber>
			<width>32</width>
			<height>32</height>
			<Action>
				<ActionName>act1</ActionName>
				<FrameDelay>100</FrameDelay>
				<FrameTotal>1</FrameTotal>
				<IsRepeat>true</IsRepeat>
				<RepeatStart>0</RepeatStart>
				<RepeatOver>0</RepeatOver>
				<FrameBox>
					<Frame>
						<x>32</x>
						<y>64</y>
						<rectBox>
							<rectNumber>1</rectNumber>
							<rect>
								<x>0</x>
								<y>-10</y>
								<w>25</w>
								<h>25</h>
							</rect>
						</rectBox>
					</Frame>
				</FrameBox>
			</Action>
		</Sprite>
		<Sprite>
			<SpriteName>stone0Winter</SpriteName>
			<PictureName>\resource\picture\decoration\decoration.png</PictureName>
			<TotalActionNumber>1</TotalActionNumber>
			<width>32</width>
			<height>32</height>
			<Action>
				<ActionName>act1</ActionName>
				<FrameDelay>100</FrameDelay>
				<FrameTotal>1</FrameTotal>
				<IsRepeat>true</IsRepeat>
				<RepeatStart>0</RepeatStart>
				<RepeatOver>0</RepeatOver>
				<FrameBox>
					<Frame>
						<x>64</x>
						<y>64</y>
						<rectBox>
							<rectNumber>1</rectNumber>
							<rect>
								<x>0</x>
								<y>-10</y>
								<w>25</w>
								<h>25</h>
							</rect>
						</rectBox>
					</Frame>
				</FrameBox>
			</Action>
		</Sprite>
		<Sprite>
			<SpriteName>stone1Winter</SpriteName>
			<PictureName>\resource\picture\decoration\decoration.png</PictureName>
			<TotalActionNumber>1</TotalActionNumber>
			<width>32</width>
			<height>32</height>
			<Action>
				<ActionName>act1</ActionName>
				<FrameDelay>100</FrameDelay>
				<FrameTotal>1</FrameTotal>
				<IsRepeat>true</IsRepeat>
				<RepeatStart>0</RepeatStart>
				<RepeatOver>0</RepeatOver>
				<FrameBox>
					<Frame>
						<x>96</x>
						<y>64</y>
						<rectBox>
							<rectNumber>1</rectNumber>
							<rect>
								<x>0</x>
								<y>-10</y>
								<w>25</w>
								<h>25</h>
							</rect>
						</rectBox>
					</Frame>
				</FrameBox>
			</Action>
		</Sprite>
		<Sprite>
			<SpriteName>tree0Small</SpriteName>
			<PictureName>\resource\picture\decoration\decoration.png</PictureName>
			<TotalActionNumber>1</TotalActionNumber>
			<width>32</width>
			<height>32</height>
			<Action>
				<ActionName>act1</ActionName>
				<FrameDelay>100</FrameDelay>
				<FrameTotal>1</FrameTotal>
				<IsRepeat>true</IsRepeat>
				<RepeatStart>0</RepeatStart>
				<RepeatOver>0</RepeatOver>
				<FrameBox>
					<Frame>
						<x>0</x>
						<y>96</y>
						<rectBox>
							<rectNumber>1</rectNumber>
							<rect>
								<x>0</x>
								<y>-10</y>
								<w>25</w>
								<h>25</h>
							</rect>
						</rectBox>
					</Frame>
				</FrameBox>
			</Action>
		</Sprite>
		<Sprite>
			<SpriteName>tree1Small</SpriteName>
			<PictureName>\resource\picture\decoration\decoration.png</PictureName>
			<TotalActionNumber>1</TotalActionNumber>
			<width>32</width>
			<height>32</height>
			<Action>
				<ActionName>act1</ActionName>
				<FrameDelay>100</FrameDelay>
				<FrameTotal>1</FrameTotal>
				<IsRepeat>true</IsRepeat>
				<RepeatStart>0</RepeatStart>
				<RepeatOver>0</RepeatOver>
				<FrameBox>
					<Frame>
						<x>32</x>
						<y>96</y>
						<rectBox>
							<rectNumber>1</rectNumber>
							<rect>
								<x>0</x>
								<y>-10</y>
								<w>25</w>
								<h>25</h>
							</rect>
						</rectBox>
					</Frame>
				</FrameBox>
			</Action>
		</Sprite>
		<Sprite>
			<SpriteName>tree2Small</SpriteName>
			<PictureName>\resource\picture\decoration\decoration.png</PictureName>
			<TotalActionNumber>1</TotalActionNumber>
			<width>32</width>
			<height>32</height>
			<Action>
				<ActionName>act1</ActionName>
				<FrameDelay>100</FrameDelay>
				<FrameTotal>1</FrameTotal>
				<IsRepeat>true</IsRepeat>
				<RepeatStart>0</RepeatStart>
				<RepeatOver>0</RepeatOver>
				<FrameBox>
					<Frame>
						<x>64</x>
						<y>96</y>
						<rectBox>
							<rectNumber>1</rectNumber>
							<rect>
								<x>0</x>
								<y>-10</y>
								<w>25</w>
								<h>25</h>
							</rect>
						</rectBox>
					</Frame>
				</FrameBox>
			</Action>
		</Sprite>
		<Sprite>
			<SpriteName>tree3Small</SpriteName>
			<PictureName>\resource\picture\decoration\decoration.png</PictureName>
			<TotalActionNumber>1</TotalActionNumber>
			<width>32</width>
			<height>32</height>
			<Action>
				<ActionName>act1</ActionName>
				<FrameDelay>100</FrameDelay>
				<FrameTotal>1</FrameTotal>
				<IsRepeat>true</IsRepeat>
				<RepeatStart>0</RepeatStart>
				<RepeatOver>0</RepeatOver>
				<FrameBox>
					<Frame>
						<x>96</x>
						<y>96</y>
						<rectBox>
							<rectNumber>1</rectNumber>
							<rect>
								<x>0</x>
								<y>-10</y>
								<w>25</w>
								<h>25</h>
							</rect>
						</rectBox>
					</Frame>
				</FrameBox>
			</Action>
		</Sprite>
		<Sprite>
			<SpriteName>flowerShrub</SpriteName>
			<PictureName>\resource\picture\decoration\decoration.png</PictureName>
			<TotalActionNumber>1</TotalActionNumber>
			<width>32</width>
			<height>32</height>
			<Action>
				<ActionName>act1</ActionName>
				<FrameDelay>100</FrameDelay>
				<FrameTotal>1</FrameTotal>
				<IsRepeat>true</IsRepeat>
				<RepeatStart>0</RepeatStart>
				<RepeatOver>0</RepeatOver>
				<FrameBox>
					<Frame>
						<x>128</x>
						<y>96</y>
						<rectBox>
							<rectNumber>1</rectNumber>
							<rect>
								<x>0</x>
								<y>-10</y>
								<w>25</w>
								<h>25</h>
							</rect>
						</rectBox>
					</Frame>
				</FrameBox>
			</Action>
		</Sprite>
		<Sprite>
			<SpriteName>rafflesia</SpriteName>
			<PictureName>\resource\picture\decoration\decoration.png</PictureName>
			<TotalActionNumber>1</TotalActionNumber>
			<width>32</width>
			<height>32</height>
			<Action>
				<ActionName>act1</ActionName>
				<FrameDelay>100</FrameDelay>
				<FrameTotal>1</FrameTotal>
				<IsRepeat>true</IsRepeat>
				<RepeatStart>0</RepeatStart>
				<RepeatOver>0</RepeatOver>
				<FrameBox>
					<Frame>
						<x>160</x>
						<y>96</y>
						<rectBox>
							<rectNumber>1</rectNumber>
							<rect>
								<x>0</x>
								<y>-10</y>
								<w>20</w>
								<h>20</h>
							</rect>
						</rectBox>
					</Frame>
				</FrameBox>
			</Action>
		</Sprite>
		<Sprite>
			<SpriteName>tree0</SpriteName>
			<PictureName>\resource\picture\decoration\decoration.png</PictureName>
			<TotalActionNumber>1</TotalActionNumber>
			<width>32</width>
			<height>64</height>
			<Action>
				<ActionName>act1</ActionName>
				<FrameDelay>100</FrameDelay>
				<FrameTotal>1</FrameTotal>
				<IsRepeat>true</IsRepeat>
				<RepeatStart>0</RepeatStart>
				<RepeatOver>0</RepeatOver>
				<FrameBox>
					<Frame>
						<x>0</x>
						<y>128</y>
						<rectBox>
							<rectNumber>1</rectNumber>
							<rect>
								<x>0</x>
								<y>-32</y>
								<w>20</w>
								<h>20</h>
							</rect>
						</rectBox>
					</Frame>
				</FrameBox>
			</Action>
		</Sprite>
		<Sprite>
			<SpriteName>tree1</SpriteName>
			<PictureName>\resource\picture\decoration\decoration.png</PictureName>
			<TotalActionNumber>1</TotalActionNumber>
			<width>32</width>
			<height>64</height>
			<Action>
				<ActionName>act1</ActionName>
				<FrameDelay>100</FrameDelay>
				<FrameTotal>1</FrameTotal>
				<IsRepeat>true</IsRepeat>
				<RepeatStart>0</RepeatStart>
				<RepeatOver>0</RepeatOver>
				<FrameBox>
					<Frame>
						<x>32</x>
						<y>128</y>
						<rectBox>
							<rectNumber>1</rectNumber>
							<rect>
								<x>0</x>
								<y>-32</y>
								<w>20</w>
								<h>20</h>
							</rect>
						</rectBox>
					</Frame>
				</FrameBox>
			</Action>
		</Sprite>
		<Sprite>
			<SpriteName>tree2</SpriteName>
			<PictureName>\resource\picture\decoration\decoration.png</PictureName>
			<TotalActionNumber>1</TotalActionNumber>
			<width>32</width>
			<height>64</height>
			<Action>
				<ActionName>act1</ActionName>
				<FrameDelay>100</FrameDelay>
				<FrameTotal>1</FrameTotal>
				<IsRepeat>true</IsRepeat>
				<RepeatStart>0</RepeatStart>
				<RepeatOver>0</RepeatOver>
				<FrameBox>
					<Frame>
						<x>64</x>
						<y>128</y>
						<rectBox>
							<rectNumber>1</rectNumber>
							<rect>
								<x>0</x>
								<y>-32</y>
								<w>20</w>
								<h>20</h>
							</rect>
						</rectBox>
					</Frame>
				</FrameBox>
			</Action>
		</Sprite>
		<Sprite>
			<SpriteName>tree3</SpriteName>
			<PictureName>\resource\picture\decoration\decoration.png</PictureName>
			<TotalActionNumber>1</TotalActionNumber>
			<width>32</width>
			<height>64</height>
			<Action>
				<ActionName>act1</ActionName>
				<FrameDelay>100</FrameDelay>
				<FrameTotal>1</FrameTotal>
				<IsRepeat>true</IsRepeat>
				<RepeatStart>0</RepeatStart>
				<RepeatOver>0</RepeatOver>
				<FrameBox>
					<Frame>
						<x>96</x>
						<y>128</y>
						<rectBox>
							<rectNumber>1</rectNumber>
							<rect>
								<x>0</x>
								<y>-32</y>
								<w>20</w>
								<h>20</h>
							</rect>
						</rectBox>
					</Frame>
				</FrameBox>
			</Action>
		</Sprite>
		<Sprite>
			<SpriteName>cirrus</SpriteName>
			<PictureName>\resource\picture\decoration\decoration.png</PictureName>
			<TotalActionNumber>1</TotalActionNumber>
			<width>32</width>
			<height>64</height>
			<Action>
				<ActionName>act1</ActionName>
				<FrameDelay>100</FrameDelay>
				<FrameTotal>1</FrameTotal>
				<IsRepeat>true</IsRepeat>
				<RepeatStart>0</RepeatStart>
				<RepeatOver>0</RepeatOver>
				<FrameBox>
					<Frame>
						<x>128</x>
						<y>128</y>
						<rectBox>
							<rectNumber>1</rectNumber>
							<rect>
								<x>0</x>
								<y>-32</y>
								<w>20</w>
								<h>20</h>
							</rect>
						</rectBox>
					</Frame>
				</FrameBox>
			</Action>
		</Sprite>
		<Sprite>
			<SpriteName>deadman0</SpriteName>
			<PictureName>\resource\picture\decoration\decoration.png</PictureName>
			<TotalActionNumber>1</TotalActionNumber>
			<width>32</width>
			<height>32</height>
			<Action>
				<ActionName>act1</ActionName>
				<FrameDelay>100</FrameDelay>
				<FrameTotal>1</FrameTotal>
				<IsRepeat>true</IsRepeat>
				<RepeatStart>0</RepeatStart>
				<RepeatOver>0</RepeatOver>
				<FrameBox>
					<Frame>
						<x>160</x>
						<y>128</y>
						<rectBox>
							<rectNumber>0</rectNumber>
						</rectBox>
					</Frame>
				</FrameBox>
			</Action>
		</Sprite>
		<Sprite>
			<SpriteName>deadman2</SpriteName>
			<PictureName>\resource\picture\decoration\decoration.png</PictureName>
			<TotalActionNumber>1</TotalActionNumber>
			<width>32</width>
			<height>32</height>
			<Action>
				<ActionName>act1</ActionName>
				<FrameDelay>100</FrameDelay>
				<FrameTotal>1</FrameTotal>
				<IsRepeat>true</IsRepeat>
				<RepeatStart>0</RepeatStart>
				<RepeatOver>0</RepeatOver>
				<FrameBox>
					<Frame>
						<x>192</x>
						<y>128</y>
						<rectBox>
							<rectNumber>0</rectNumber>
						</rectBox>
					</Frame>
				</FrameBox>
			</Action>
		</Sprite>
		<Sprite>
			<SpriteName>deadman3</SpriteName>
			<PictureName>\resource\picture\decoration\decoration.png</PictureName>
			<TotalActionNumber>1</TotalActionNumber>
			<width>32</width>
			<height>32</height>
			<Action>
				<ActionName>act1</ActionName>
				<FrameDelay>100</FrameDelay>
				<FrameTotal>1</FrameTotal>
				<IsRepeat>true</IsRepeat>
				<RepeatStart>0</RepeatStart>
				<RepeatOver>0</RepeatOver>
				<FrameBox>
					<Frame>
						<x>224</x>
						<y>128</y>
						<rectBox>
							<rectNumber>0</rectNumber>
						</rectBox>
					</Frame>
				</FrameBox>
			</Action>
		</Sprite>
		<Sprite>
			<SpriteName>flower0</SpriteName>
			<PictureName>\resource\picture\decoration\decoration.png</PictureName>
			<TotalActionNumber>1</TotalActionNumber>
			<width>32</width>
			<height>32</height>
			<Action>
				<ActionName>act1</ActionName>
				<FrameDelay>100</FrameDelay>
				<FrameTotal>1</FrameTotal>
				<IsRepeat>true</IsRepeat>
				<RepeatStart>0</RepeatStart>
				<RepeatOver>0</RepeatOver>
				<FrameBox>
					<Frame>
						<x>0</x>
						<y>192</y>
						<rectBox>
							<rectNumber>0</rectNumber>
						</rectBox>
					</Frame>
				</FrameBox>
			</Action>
		</Sprite>
		<Sprite>
			<SpriteName>flower1</SpriteName>
			<PictureName>\resource\picture\decoration\decoration.png</PictureName>
			<TotalActionNumber>1</TotalActionNumber>
			<width>32</width>
			<height>32</height>
			<Action>
				<ActionName>act1</ActionName>
				<FrameDelay>100</FrameDelay>
				<FrameTotal>1</FrameTotal>
				<IsRepeat>true</IsRepeat>
				<RepeatStart>0</RepeatStart>
				<RepeatOver>0</RepeatOver>
				<FrameBox>
					<Frame>
						<x>32</x>
						<y>192</y>
						<rectBox>
							<rectNumber>0</rectNumber>
						</rectBox>
					</Frame>
				</FrameBox>
			</Action>
		</Sprite>
		<Sprite>
			<SpriteName>flower2</SpriteName>
			<PictureName>\resource\picture\decoration\decoration.png</PictureName>
			<TotalActionNumber>1</TotalActionNumber>
			<width>32</width>
			<height>32</height>
			<Action>
				<ActionName>act1</ActionName>
				<FrameDelay>100</FrameDelay>
				<FrameTotal>1</FrameTotal>
				<IsRepeat>true</IsRepeat>
				<RepeatStart>0</RepeatStart>
				<RepeatOver>0</RepeatOver>
				<FrameBox>
					<Frame>
						<x>64</x>
						<y>192</y>
						<rectBox>
							<rectNumber>0</rectNumber>
						</rectBox>
					</Frame>
				</FrameBox>
			</Action>
		</Sprite>
		<Sprite>
			<SpriteName>flower3</SpriteName>
			<PictureName>\resource\picture\decoration\decoration.png</PictureName>
			<TotalActionNumber>1</TotalActionNumber>
			<width>32</width>
			<height>32</height>
			<Action>
				<ActionName>act1</ActionName>
				<FrameDelay>100</FrameDelay>
				<FrameTotal>1</FrameTotal>
				<IsRepeat>true</IsRepeat>
				<RepeatStart>0</RepeatStart>
				<RepeatOver>0</RepeatOver>
				<FrameBox>
					<Frame>
						<x>96</x>
						<y>192</y>
						<rectBox>
							<rectNumber>0</rectNumber>
						</rectBox>
					</Frame>
				</FrameBox>
			</Action>
		</Sprite>
		<Sprite>
			<SpriteName>vegetable0</SpriteName>
			<PictureName>\resource\picture\decoration\decoration.png</PictureName>
			<TotalActionNumber>1</TotalActionNumber>
			<width>32</width>
			<height>32</height>
			<Action>
				<ActionName>act1</ActionName>
				<FrameDelay>100</FrameDelay>
				<FrameTotal>1</FrameTotal>
				<IsRepeat>true</IsRepeat>
				<RepeatStart>0</RepeatStart>
				<RepeatOver>0</RepeatOver>
				<FrameBox>
					<Frame>
						<x>128</x>
						<y>192</y>
						<rectBox>
							<rectNumber>0</rectNumber>
						</rectBox>
					</Frame>
				</FrameBox>
			</Action>
		</Sprite>
		<Sprite>
			<SpriteName>vegetable1</SpriteName>
			<PictureName>\resource\picture\decoration\decoration.png</PictureName>
			<TotalActionNumber>1</TotalActionNumber>
			<width>32</width>
			<height>32</height>
			<Action>
				<ActionName>act1</ActionName>
				<FrameDelay>100</FrameDelay>
				<FrameTotal>1</FrameTotal>
				<IsRepeat>true</IsRepeat>
				<RepeatStart>0</RepeatStart>
				<RepeatOver>0</RepeatOver>
				<FrameBox>
					<Frame>
						<x>160</x>
						<y>192</y>
						<rectBox>
							<rectNumber>0</rectNumber>
						</rectBox>
					</Frame>
				</FrameBox>
			</Action>
		</Sprite>
		<Sprite>
			<SpriteName>vegetable2</SpriteName>
			<PictureName>\resource\picture\decoration\decoration.png</PictureName>
			<TotalActionNumber>1</TotalActionNumber>
			<width>32</width>
			<height>32</height>
			<Action>
				<ActionName>act1</ActionName>
				<FrameDelay>100</FrameDelay>
				<FrameTotal>1</FrameTotal>
				<IsRepeat>true</IsRepeat>
				<RepeatStart>0</RepeatStart>
				<RepeatOver>0</RepeatOver>
				<FrameBox>
					<Frame>
						<x>192</x>
						<y>192</y>
						<rectBox>
							<rectNumber>0</rectNumber>
						</rectBox>
					</Frame>
				</FrameBox>
			</Action>
		</Sprite>
		<Sprite>
			<SpriteName>vegetable3</SpriteName>
			<PictureName>\resource\picture\decoration\decoration.png</PictureName>
			<TotalActionNumber>1</TotalActionNumber>
			<width>32</width>
			<height>32</height>
			<Action>
				<ActionName>act1</ActionName>
				<FrameDelay>100</FrameDelay>
				<FrameTotal>1</FrameTotal>
				<IsRepeat>true</IsRepeat>
				<RepeatStart>0</RepeatStart>
				<RepeatOver>0</RepeatOver>
				<FrameBox>
					<Frame>
						<x>224</x>
						<y>192</y>
						<rectBox>
							<rectNumber>0</rectNumber>
						</rectBox>
					</Frame>
				</FrameBox>
			</Action>
		</Sprite>
		<Sprite>
			<SpriteName>mushroom0</SpriteName>
			<PictureName>\resource\picture\decoration\decoration.png</PictureName>
			<TotalActionNumber>1</TotalActionNumber>
			<width>32</width>
			<height>32</height>
			<Action>
				<ActionName>act1</ActionName>
				<FrameDelay>100</FrameDelay>
				<FrameTotal>1</FrameTotal>
				<IsRepeat>true</IsRepeat>
				<RepeatStart>0</RepeatStart>
				<RepeatOver>0</RepeatOver>
				<FrameBox>
					<Frame>
						<x>256</x>
						<y>192</y>
						<rectBox>
							<rectNumber>0</rectNumber>
						</rectBox>
					</Frame>
				</FrameBox>
			</Action>
		</Sprite>
		<Sprite>
			<SpriteName>mushroom1</SpriteName>
			<PictureName>\resource\picture\decoration\decoration.png</PictureName>
			<TotalActionNumber>1</TotalActionNumber>
			<width>32</width>
			<height>32</height>
			<Action>
				<ActionName>act1</ActionName>
				<FrameDelay>100</FrameDelay>
				<FrameTotal>1</FrameTotal>
				<IsRepeat>true</IsRepeat>
				<RepeatStart>0</RepeatStart>
				<RepeatOver>0</RepeatOver>
				<FrameBox>
					<Frame>
						<x>288</x>
						<y>192</y>
						<rectBox>
							<rectNumber>0</rectNumber>
						</rectBox>
					</Frame>
				</FrameBox>
			</Action>
		</Sprite>
		<Sprite>
			<SpriteName>grass0</SpriteName>
			<PictureName>\resource\picture\decoration\decoration.png</PictureName>
			<TotalActionNumber>1</TotalActionNumber>
			<width>32</width>
			<height>32</height>
			<Action>
				<ActionName>act1</ActionName>
				<FrameDelay>100</FrameDelay>
				<FrameTotal>1</FrameTotal>
				<IsRepeat>true</IsRepeat>
				<RepeatStart>0</RepeatStart>
				<RepeatOver>0</RepeatOver>
				<FrameBox>
					<Frame>
						<x>0</x>
						<y>224</y>
						<rectBox>
							<rectNumber>0</rectNumber>
						</rectBox>
					</Frame>
				</FrameBox>
			</Action>
		</Sprite>
		<Sprite>
			<SpriteName>grass1</SpriteName>
			<PictureName>\resource\picture\decoration\decoration.png</PictureName>
			<TotalActionNumber>1</TotalActionNumber>
			<width>32</width>
			<height>32</height>
			<Action>
				<ActionName>act1</ActionName>
				<FrameDelay>100</FrameDelay>
				<FrameTotal>1</FrameTotal>
				<IsRepeat>true</IsRepeat>
				<RepeatStart>0</RepeatStart>
				<RepeatOver>0</RepeatOver>
				<FrameBox>
					<Frame>
						<x>32</x>
						<y>224</y>
						<rectBox>
							<rectNumber>0</rectNumber>
						</rectBox>
					</Frame>
				</FrameBox>
			</Action>
		</Sprite>
		<Sprite>
			<SpriteName>grass2</SpriteName>
			<PictureName>\resource\picture\decoration\decoration.png</PictureName>
			<TotalActionNumber>1</TotalActionNumber>
			<width>32</width>
			<height>32</height>
			<Action>
				<ActionName>act1</ActionName>
				<FrameDelay>100</FrameDelay>
				<FrameTotal>1</FrameTotal>
				<IsRepeat>true</IsRepeat>
				<RepeatStart>0</RepeatStart>
				<RepeatOver>0</RepeatOver>
				<FrameBox>
					<Frame>
						<x>64</x>
						<y>224</y>
						<rectBox>
							<rectNumber>0</rectNumber>
						</rectBox>
					</Frame>
				</FrameBox>
			</Action>
		</Sprite>
		<Sprite>
			<SpriteName>grass3</SpriteName>
			<PictureName>\resource\picture\decoration\decoration.png</PictureName>
			<TotalActionNumber>1</TotalActionNumber>
			<width>32</width>
			<height>32</height>
			<Action>
				<ActionName>act1</ActionName>
				<FrameDelay>100</FrameDelay>
				<FrameTotal>1</FrameTotal>
				<IsRepeat>true</IsRepeat>
				<RepeatStart>0</RepeatStart>
				<RepeatOver>0</RepeatOver>
				<FrameBox>
					<Frame>
						<x>96</x>
						<y>224</y>
						<rectBox>
							<rectNumber>0</rectNumber>
						</rectBox>
					</Frame>
				</FrameBox>
			</Action>
		</Sprite>
		<Sprite>
			<SpriteName>grass0Winter</SpriteName>
			<PictureName>\resource\picture\decoration\decoration.png</PictureName>
			<TotalActionNumber>1</TotalActionNumber>
			<width>32</width>
			<height>32</height>
			<Action>
				<ActionName>act1</ActionName>
				<FrameDelay>100</FrameDelay>
				<FrameTotal>1</FrameTotal>
				<IsRepeat>true</IsRepeat>
				<RepeatStart>0</RepeatStart>
				<RepeatOver>0</RepeatOver>
				<FrameBox>
					<Frame>
						<x>128</x>
						<y>224</y>
						<rectBox>
							<rectNumber>0</rectNumber>
						</rectBox>
					</Frame>
				</FrameBox>
			</Action>
		</Sprite>
		<Sprite>
			<SpriteName>grass1Winter</SpriteName>
			<PictureName>\resource\picture\decoration\decoration.png</PictureName>
			<TotalActionNumber>1</TotalActionNumber>
			<width>32</width>
			<height>32</height>
			<Action>
				<ActionName>act1</ActionName>
				<FrameDelay>100</FrameDelay>
				<FrameTotal>1</FrameTotal>
				<IsRepeat>true</IsRepeat>
				<RepeatStart>0</RepeatStart>
				<RepeatOver>0</RepeatOver>
				<FrameBox>
					<Frame>
						<x>160</x>
						<y>224</y>
						<rectBox>
							<rectNumber>0</rectNumber>
						</rectBox>
					</Frame>
				</FrameBox>
			</Action>
		</Sprite>
		<Sprite>
			<SpriteName>grass2Winter</SpriteName>
			<PictureName>\resource\picture\decoration\decoration.png</PictureName>
			<TotalActionNumber>1</TotalActionNumber>
			<width>32</width>
			<height>32</height>
			<Action>
				<ActionName>act1</ActionName>
				<FrameDelay>100</FrameDelay>
				<FrameTotal>1</FrameTotal>
				<IsRepeat>true</IsRepeat>
				<RepeatStart>0</RepeatStart>
				<RepeatOver>0</RepeatOver>
				<FrameBox>
					<Frame>
						<x>192</x>
						<y>224</y>
						<rectBox>
							<rectNumber>0</rectNumber>
						</rectBox>
					</Frame>
				</FrameBox>
			</Action>
		</Sprite>
		<Sprite>
			<SpriteName>grass3Winter</SpriteName>
			<PictureName>\resource\picture\decoration\decoration.png</PictureName>
			<TotalActionNumber>1</TotalActionNumber>
			<width>32</width>
			<height>32</height>
			<Action>
				<ActionName>act1</ActionName>
				<FrameDelay>100</FrameDelay>
				<FrameTotal>1</FrameTotal>
				<IsRepeat>true</IsRepeat>
				<RepeatStart>0</RepeatStart>
				<RepeatOver>0</RepeatOver>
				<FrameBox>
					<Frame>
						<x>224</x>
						<y>224</y>
						<rectBox>
							<rectNumber>0</rectNumber>
						</rectBox>
					</Frame>
				</FrameBox>
			</Action>
		</Sprite>
		<Sprite>
			<SpriteName>targetCircle</SpriteName>
			<PictureName>\resource\picture\decoration\target.png</PictureName>
			<TotalActionNumber>1</TotalActionNumber>
			<width>48</width>
			<height>48</height>
			<Action>
				<ActionName>targetCircle</ActionName>
				<FrameDelay>5</FrameDelay>
				<FrameTotal>4</FrameTotal>
				<IsRepeat>true</IsRepeat>
				<RepeatStart>0</RepeatStart>
				<RepeatOver>3</RepeatOver>
				<FrameBox>
					<Frame>
						<x>0</x>
						<y>0</y>
						<rectBox>
							<rectNumber>0</rectNumber>
						</rectBox>
					</Frame>
					<Frame>
						<x>48</x>
						<y>0</y>
						<rectBox>
							<rectNumber>0</rectNumber>
						</rectBox>
					</Frame>
					<Frame>
						<x>96</x>
						<y>0</y>
						<rectBox>
							<rectNumber>0</rectNumber>
						</rectBox>
					</Frame>
					<Frame>
						<x>144</x>
						<y>0</y>
						<rectBox>
							<rectNumber>0</rectNumber>
						</rectBox>
					</Frame>
				</FrameBox>
			</Action>
		</Sprite>
		<Sprite>
			<SpriteName>shadow</SpriteName>
			<PictureName>\resource\picture\decoration\decoration1.png</PictureName>
			<TotalActionNumber>1</TotalActionNumber>
			<width>32</width>
			<height>32</height>
			<Action>
				<ActionName>shadow</ActionName>
				<FrameDelay>100</FrameDelay>
				<FrameTotal>1</FrameTotal>
				<IsRepeat>false</IsRepeat>
				<RepeatStart>0</RepeatStart>
				<RepeatOver>0</RepeatOver>
				<FrameBox>
					<Frame>
						<x>480</x>
						<y>352</y>
						<rectBox>
							<rectNumber>0</rectNumber>
						</rectBox>
					</Frame>
				</FrameBox>
			</Action>
		</Sprite>
	</DecorationSprite>
	<BackgroundSprite>
		<TotalSpriteNumber>16</TotalSpriteNumber>
		<Sprite>
			<SpriteName>stone0BK</SpriteName>
			<PictureName>\resource\picture\terrain\stone0.png</PictureName>
			<TotalActionNumber>1</TotalActionNumber>
			<width>32</width>
			<height>32</height>
			<Action>
				<ActionName>act1</ActionName>
				<FrameDelay>100</FrameDelay>
				<FrameTotal>1</FrameTotal>
				<IsRepeat>false</IsRepeat>
				<RepeatStart>0</RepeatStart>
				<RepeatOver>0</RepeatOver>
				<FrameBox>
					<Frame>
						<x>0</x>
						<y>0</y>
						<rectBox>
							<rectNumber>0</rectNumber>
						</rectBox>
					</Frame>
				</FrameBox>
			</Action>
		</Sprite>
		<Sprite>
			<SpriteName>clothBK</SpriteName>
			<PictureName>\resource\picture\terrain\cloth.png</PictureName>
			<TotalActionNumber>1</TotalActionNumber>
			<width>32</width>
			<height>32</height>
			<Action>
				<ActionName>act1</ActionName>
				<FrameDelay>100</FrameDelay>
				<FrameTotal>1</FrameTotal>
				<IsRepeat>false</IsRepeat>
				<RepeatStart>0</RepeatStart>
				<RepeatOver>0</RepeatOver>
				<FrameBox>
					<Frame>
						<x>0</x>
						<y>0</y>
						<rectBox>
							<rectNumber>0</rectNumber>
						</rectBox>
					</Frame>
				</FrameBox>
			</Action>
		</Sprite>
		<Sprite>
			<SpriteName>mudBK</SpriteName>
			<PictureName>\resource\picture\terrain\mud.png</PictureName>
			<TotalActionNumber>1</TotalActionNumber>
			<width>32</width>
			<height>32</height>
			<Action>
				<ActionName>act1</ActionName>
				<FrameDelay>100</FrameDelay>
				<FrameTotal>1</FrameTotal>
				<IsRepeat>false</IsRepeat>
				<RepeatStart>0</RepeatStart>
				<RepeatOver>0</RepeatOver>
				<FrameBox>
					<Frame>
						<x>0</x>
						<y>0</y>
						<rectBox>
							<rectNumber>0</rectNumber>
						</rectBox>
					</Frame>
				</FrameBox>
			</Action>
		</Sprite>
		<Sprite>
			<SpriteName>mudRedBK</SpriteName>
			<PictureName>\resource\picture\terrain\mudRed.png</PictureName>
			<TotalActionNumber>1</TotalActionNumber>
			<width>32</width>
			<height>32</height>
			<Action>
				<ActionName>act1</ActionName>
				<FrameDelay>100</FrameDelay>
				<FrameTotal>1</FrameTotal>
				<IsRepeat>false</IsRepeat>
				<RepeatStart>0</RepeatStart>
				<RepeatOver>0</RepeatOver>
				<FrameBox>
					<Frame>
						<x>0</x>
						<y>0</y>
						<rectBox>
							<rectNumber>0</rectNumber>
						</rectBox>
					</Frame>
				</FrameBox>
			</Action>
		</Sprite>
		<Sprite>
			<SpriteName>grassSummerBK</SpriteName>
			<PictureName>\resource\picture\terrain\grassSummer.png</PictureName>
			<TotalActionNumber>1</TotalActionNumber>
			<width>32</width>
			<height>32</height>
			<Action>
				<ActionName>act1</ActionName>
				<FrameDelay>100</FrameDelay>
				<FrameTotal>1</FrameTotal>
				<IsRepeat>false</IsRepeat>
				<RepeatStart>0</RepeatStart>
				<RepeatOver>0</RepeatOver>
				<FrameBox>
					<Frame>
						<x>0</x>
						<y>0</y>
						<rectBox>
							<rectNumber>0</rectNumber>
						</rectBox>
					</Frame>
				</FrameBox>
			</Action>
		</Sprite>
		<Sprite>
			<SpriteName>grassAutumnBK</SpriteName>
			<PictureName>\resource\picture\terrain\grassAutumn.png</PictureName>
			<TotalActionNumber>1</TotalActionNumber>
			<width>32</width>
			<height>32</height>
			<Action>
				<ActionName>act1</ActionName>
				<FrameDelay>100</FrameDelay>
				<FrameTotal>1</FrameTotal>
				<IsRepeat>false</IsRepeat>
				<RepeatStart>0</RepeatStart>
				<RepeatOver>0</RepeatOver>
				<FrameBox>
					<Frame>
						<x>0</x>
						<y>0</y>
						<rectBox>
							<rectNumber>0</rectNumber>
						</rectBox>
					</Frame>
				</FrameBox>
			</Action>
		</Sprite>
		<Sprite>
			<SpriteName>grassSpringBK</SpriteName>
			<PictureName>\resource\picture\terrain\grassSpring.png</PictureName>
			<TotalActionNumber>1</TotalActionNumber>
			<width>32</width>
			<height>32</height>
			<Action>
				<ActionName>act1</ActionName>
				<FrameDelay>100</FrameDelay>
				<FrameTotal>1</FrameTotal>
				<IsRepeat>false</IsRepeat>
				<RepeatStart>0</RepeatStart>
				<RepeatOver>0</RepeatOver>
				<FrameBox>
					<Frame>
						<x>0</x>
						<y>0</y>
						<rectBox>
							<rectNumber>0</rectNumber>
						</rectBox>
					</Frame>
				</FrameBox>
			</Action>
		</Sprite>
		<Sprite>
			<SpriteName>grassWinterBK</SpriteName>
			<PictureName>\resource\picture\terrain\grassWinter.png</PictureName>
			<TotalActionNumber>1</TotalActionNumber>
			<width>32</width>
			<height>32</height>
			<Action>
				<ActionName>act1</ActionName>
				<FrameDelay>100</FrameDelay>
				<FrameTotal>1</FrameTotal>
				<IsRepeat>false</IsRepeat>
				<RepeatStart>0</RepeatStart>
				<RepeatOver>0</RepeatOver>
				<FrameBox>
					<Frame>
						<x>0</x>
						<y>0</y>
						<rectBox>
							<rectNumber>0</rectNumber>
						</rectBox>
					</Frame>
				</FrameBox>
			</Action>
		</Sprite>
		<Sprite>
			<SpriteName>grass0BK</SpriteName>
			<PictureName>\resource\picture\terrain\grass0.png</PictureName>
			<TotalActionNumber>1</TotalActionNumber>
			<width>32</width>
			<height>32</height>
			<Action>
				<ActionName>act1</ActionName>
				<FrameDelay>100</FrameDelay>
				<FrameTotal>1</FrameTotal>
				<IsRepeat>false</IsRepeat>
				<RepeatStart>0</RepeatStart>
				<RepeatOver>0</RepeatOver>
				<FrameBox>
					<Frame>
						<x>0</x>
						<y>0</y>
						<rectBox>
							<rectNumber>0</rectNumber>
						</rectBox>
					</Frame>
				</FrameBox>
			</Action>
		</Sprite>
		<Sprite>
			<SpriteName>sand0BK</SpriteName>
			<PictureName>\resource\picture\terrain\sand0.png</PictureName>
			<TotalActionNumber>1</TotalActionNumber>
			<width>32</width>
			<height>32</height>
			<Action>
				<ActionName>act1</ActionName>
				<FrameDelay>100</FrameDelay>
				<FrameTotal>1</FrameTotal>
				<IsRepeat>false</IsRepeat>
				<RepeatStart>0</RepeatStart>
				<RepeatOver>0</RepeatOver>
				<FrameBox>
					<Frame>
						<x>0</x>
						<y>0</y>
						<rectBox>
							<rectNumber>0</rectNumber>
						</rectBox>
					</Frame>
				</FrameBox>
			</Action>
		</Sprite>
		<Sprite>
			<SpriteName>sand1BK</SpriteName>
			<PictureName>\resource\picture\terrain\sand1.png</PictureName>
			<TotalActionNumber>1</TotalActionNumber>
			<width>32</width>
			<height>32</height>
			<Action>
				<ActionName>act1</ActionName>
				<FrameDelay>100</FrameDelay>
				<FrameTotal>1</FrameTotal>
				<IsRepeat>false</IsRepeat>
				<RepeatStart>0</RepeatStart>
				<RepeatOver>0</RepeatOver>
				<FrameBox>
					<Frame>
						<x>0</x>
						<y>0</y>
						<rectBox>
							<rectNumber>0</rectNumber>
						</rectBox>
					</Frame>
				</FrameBox>
			</Action>
		</Sprite>
		<Sprite>
			<SpriteName>snow0BK</SpriteName>
			<PictureName>\resource\picture\terrain\snow0.png</PictureName>
			<TotalActionNumber>1</TotalActionNumber>
			<width>32</width>
			<height>32</height>
			<Action>
				<ActionName>act1</ActionName>
				<FrameDelay>100</FrameDelay>
				<FrameTotal>1</FrameTotal>
				<IsRepeat>false</IsRepeat>
				<RepeatStart>0</RepeatStart>
				<RepeatOver>0</RepeatOver>
				<FrameBox>
					<Frame>
						<x>0</x>
						<y>0</y>
						<rectBox>
							<rectNumber>0</rectNumber>
						</rectBox>
					</Frame>
				</FrameBox>
			</Action>
		</Sprite>
		<Sprite>
			<SpriteName>grass1BK</SpriteName>
			<PictureName>\resource\picture\terrain\grass1.png</PictureName>
			<TotalActionNumber>1</TotalActionNumber>
			<width>32</width>
			<height>32</height>
			<Action>
				<ActionName>act1</ActionName>
				<FrameDelay>100</FrameDelay>
				<FrameTotal>1</FrameTotal>
				<IsRepeat>false</IsRepeat>
				<RepeatStart>0</RepeatStart>
				<RepeatOver>0</RepeatOver>
				<FrameBox>
					<Frame>
						<x>0</x>
						<y>0</y>
						<rectBox>
							<rectNumber>0</rectNumber>
						</rectBox>
					</Frame>
				</FrameBox>
			</Action>
		</Sprite>
		<Sprite>
			<SpriteName>stone1BK</SpriteName>
			<PictureName>\resource\picture\terrain\stone1.png</PictureName>
			<TotalActionNumber>1</TotalActionNumber>
			<width>32</width>
			<height>32</height>
			<Action>
				<ActionName>act1</ActionName>
				<FrameDelay>100</FrameDelay>
				<FrameTotal>1</FrameTotal>
				<IsRepeat>false</IsRepeat>
				<RepeatStart>0</RepeatStart>
				<RepeatOver>0</RepeatOver>
				<FrameBox>
					<Frame>
						<x>0</x>
						<y>0</y>
						<rectBox>
							<rectNumber>0</rectNumber>
						</rectBox>
					</Frame>
				</FrameBox>
			</Action>
		</Sprite>
		<Sprite>
			<SpriteName>sand2BK</SpriteName>
			<PictureName>\resource\picture\terrain\sand2.png</PictureName>
			<TotalActionNumber>1</TotalActionNumber>
			<width>32</width>
			<height>32</height>
			<Action>
				<ActionName>act1</ActionName>
				<FrameDelay>100</FrameDelay>
				<FrameTotal>1</FrameTotal>
				<IsRepeat>false</IsRepeat>
				<RepeatStart>0</RepeatStart>
				<RepeatOver>0</RepeatOver>
				<FrameBox>
					<Frame>
						<x>0</x>
						<y>0</y>
						<rectBox>
							<rectNumber>0</rectNumber>
						</rectBox>
					</Frame>
				</FrameBox>
			</Action>
		</Sprite>
		<Sprite>
			<SpriteName>snow1BK</SpriteName>
			<PictureName>\resource\picture\terrain\snow1.png</PictureName>
			<TotalActionNumber>1</TotalActionNumber>
			<width>32</width>
			<height>32</height>
			<Action>
				<ActionName>act1</ActionName>
				<FrameDelay>100</FrameDelay>
				<FrameTotal>1</FrameTotal>
				<IsRepeat>false</IsRepeat>
				<RepeatStart>0</RepeatStart>
				<RepeatOver>0</RepeatOver>
				<FrameBox>
					<Frame>
						<x>0</x>
						<y>0</y>
						<rectBox>
							<rectNumber>0</rectNumber>
						</rectBox>
					</Frame>
				</FrameBox>
			</Action>
		</Sprite>
	</BackgroundSprite>
	<FaceSprite>
		<TotalSpriteNumber>1</TotalSpriteNumber>
		<Sprite>
			<SpriteName>testFace</SpriteName>
			<PictureName>\resource\picture\face\testFace.png</PictureName>
			<TotalActionNumber>1</TotalActionNumber>
			<width>300</width>
			<height>360</height>
			<Action>
				<ActionName>testFace</ActionName>
				<FrameDelay>100</FrameDelay>
				<FrameTotal>1</FrameTotal>
				<IsRepeat>false</IsRepeat>
				<RepeatStart>0</RepeatStart>
				<RepeatOver>0</RepeatOver>
				<FrameBox>
					<Frame>
						<x>0</x>
						<y>0</y>
						<rectBox>
							<rectNumber>0</rectNumber>
						</rectBox>
					</Frame>
				</FrameBox>
			</Action>
		</Sprite>
	</FaceSprite>
	<DialogSprite>
		<TotalSpriteNumber>1</TotalSpriteNumber>
		<Sprite>
			<SpriteName>dialog</SpriteName>
			<PictureName>\resource\picture\decoration\dialog.png</PictureName>
			<TotalActionNumber>1</TotalActionNumber>
			<width>1000</width>
			<height>300</height>
			<Action>
				<ActionName>dialog</ActionName>
				<FrameDelay>100</FrameDelay>
				<FrameTotal>1</FrameTotal>
				<IsRepeat>false</IsRepeat>
				<RepeatStart>0</RepeatStart>
				<RepeatOver>0</RepeatOver>
				<FrameBox>
					<Frame>
						<x>1</x>
						<y>1</y>
						<rectBox>
							<rectNumber>0</rectNumber>
						</rectBox>
					</Frame>
				</FrameBox>
			</Action>
		</Sprite>
	</DialogSprite>
</SpriteBox>
